{
  "data": [{
    "icon": "fa-users",
    "name": "人员管理",
    "childmenu": [{
      "icon": "fa-circle-o",
      "name": "schedule",
      "link": "./schedule"
    }, {
      "icon": "fa-circle-o",
      "name": "home",
      "link": "./home"
    }, {
      "icon": "fa-circle-o",
      "name": "onsen",
      "link": "./onsen"
    }]
  }, {
    "icon": "fa-hand-paper-o",
    "name": "权限管理",
    "childmenu": [{
      "icon": "fa-circle-o",
      "name": "onsen",
      "link": "./onsen"
    }, {
      "icon": "fa-circle-o",
      "name": "home",
      "link": "./home"
    }]
  }, {
    "icon": "fa-hourglass-end",
    "name": "经验值管理",
    "childmenu": [{
      "icon": "fa-circle-o",
      "name": "schedule",
      "link": "./schedule"
    }, {
      "icon": "fa-circle-o",
      "name": "home",
      "link": "./home"
    }]
  }]
}
